{
    "data": [
        {
            "id": "683a4c113e7f4",
            "unit_number": "2099",
            "description": "ddd",
            "priority": "low",
            "contact_name": "vanshh",
            "contact_email": "vanshhksharma@gmail.com",
            "status": "pending",
            "submission_date": "2025-05-31T00:23:45+00:00"
        },
        {
            "id": "683a5080a0574",
            "unit_number": "2099",
            "description": "hellooo",
            "priority": "medium",
            "contact_name": "alan",
            "contact_email": "alan@gmail.com",
            "status": "pending",
            "submission_date": "2025-05-31T00:42:40+00:00"
        }
    ]
}